<?xml version="1.0" encoding="utf-8" ?><dwsync><file name="AFFORDABLE_logo_NEW.jpg" server="s99712.gridserver.com/html/mobile/" local="3541419311" remote="318763443934280052" Dst="-1" /><file name="16921jet_2_holidays_strap_MASTER2.jpg" server="s99712.gridserver.com/html/mobile/" local="3541419311" remote="318763443934284012" Dst="-1" /><file name="Chris_Hadfield-HiRes-2013.jpg" server="s99712.gridserver.com/html/mobile/" local="3541419318" remote="318763443933233772" Dst="-1" /><file name="Chris_Hadfield-HiRes-2013_1.jpg" server="s99712.gridserver.com/html/mobile/" local="3541419318" remote="318763443933669552" Dst="-1" /><file name="MSC_Conference_Website_Banner.jpg" server="s99712.gridserver.com/html/mobile/" local="3541419318" remote="318763443933747732" Dst="-1" /><file name="Sponsor-logos-ABTA.png" server="s99712.gridserver.com/html/mobile/" local="3541419319" remote="318763443823491312" Dst="-1" /><file name="Melia_Hotels_Black_Logo.jpg" server="s99712.gridserver.com/html/mobile/" local="3541419320" remote="318763443934284132" Dst="-1" /><file name="NEW_2014_collette_logo_2c.jpg" server="s99712.gridserver.com/html/mobile/" local="3541419320" remote="318763443934283892" Dst="-1" /><file name="Standard_BA_logo_-_blue_writing_red_speedmarque_2013.jpg" server="s99712.gridserver.com/html/mobile/" local="3541419322" remote="318763443934280232" Dst="-1" /><file name="daniellevineresized.jpg" server="s99712.gridserver.com/html/mobile/" local="3541419322" remote="318763443933234132" Dst="-1" /><file name="msc_logo.jpg" server="s99712.gridserver.com/html/mobile/" local="3541419323" remote="318763443934285812" Dst="-1" /><file name="me.jpg" server="s99712.gridserver.com/html/mobile/" local="3541419323" remote="318763443934193892" Dst="-1" /><file name="ThomasCook_hori_cmyk.jpg" server="s99712.gridserver.com/html/mobile/" local="3541419324" remote="318763443934284672" Dst="-1" /><file name="photo.png" server="s99712.gridserver.com/html/mobile/" local="3541419325" remote="318763443934193232" Dst="-1" /><file name="st_blockm_slogan_blue_on_white2.jpg" server="s99712.gridserver.com/html/mobile/" local="3541419325" remote="318763443934284372" Dst="-1" /><file name="Gold_Medal_Travel_2_Stacked_Logo_2.jpg" server="s99712.gridserver.com/html/mobile/" local="3541459800" remote="323953104457720664" Dst="-1" /><file name="Caroline_Strachan.jpg" server="s99712.gridserver.com/html/mobile/" local="3541551360" remote="323953104457812224" Dst="-1" /><file name="Colin_Goldney.jpg" server="s99712.gridserver.com/html/mobile/" local="3541551180" remote="323953104457812044" Dst="-1" /><file name="Dave_Claire.jpg" server="s99712.gridserver.com/html/mobile/" local="3541551180" remote="323953104457812044" Dst="-1" /><file name="Joynt_Jennifer.jpg" server="s99712.gridserver.com/html/mobile/" local="3541551360" remote="323953104457812224" Dst="-1" /><file name="PT_on_stage_2.jpg" server="s99712.gridserver.com/html/mobile/" local="3541551240" remote="323953104457812104" Dst="-1" /><file name="PT_on_stage_2_1.jpg" server="s99712.gridserver.com/html/mobile/" local="3541551240" remote="323953104457812104" Dst="-1" /><file name="Simone_Buckley_-_high_res.png" server="s99712.gridserver.com/html/mobile/" local="3541551300" remote="323953104457812164" Dst="-1" /><file name="16921jet_2_holidays_strap_MASTER2.jpg" server="s99712.gridserver.com//html/mobile/" local="3541600849" remote="319783739185252588" Dst="-1" /><file name="AFFORDABLE_logo_NEW.jpg" server="s99712.gridserver.com//html/mobile/" local="3541600849" remote="319783739185248628" Dst="-1" /><file name="Chris_Hadfield-HiRes-2013.jpg" server="s99712.gridserver.com//html/mobile/" local="3540337260" remote="319783739184202348" Dst="-1" /><file name="Chris_Hadfield-HiRes-2013_1.jpg" server="s99712.gridserver.com//html/mobile/" local="3540773040" remote="319783739184638128" Dst="-1" /><file name="daniellevineresized.jpg" server="s99712.gridserver.com//html/mobile/" local="3540337620" remote="319783739184202708" Dst="-1" /><file name="Gold_Medal_Travel_2_Stacked_Logo_2.jpg" server="s99712.gridserver.com//html/mobile/" local="3541600851" remote="319783739185324888" Dst="-1" /><file name="Melia_Hotels_Black_Logo.jpg" server="s99712.gridserver.com//html/mobile/" local="3541600852" remote="319783739185252708" Dst="-1" /><file name="MSC_Conference_Website_Banner.jpg" server="s99712.gridserver.com//html/mobile/" local="3540851220" remote="319783739184716308" Dst="-1" /><file name="msc_logo.jpg" server="s99712.gridserver.com//html/mobile/" local="3541600854" remote="319783739185254388" Dst="-1" /><file name="NEW_2014_collette_logo_2c.jpg" server="s99712.gridserver.com//html/mobile/" local="3541600853" remote="319783739185252468" Dst="-1" /><file name="Sponsor-logos-ABTA.png" server="s99712.gridserver.com//html/mobile/" local="3430594800" remote="319783739074459888" Dst="-1" /><file name="st_blockm_slogan_blue_on_white2.jpg" server="s99712.gridserver.com//html/mobile/" local="3541600855" remote="319783739185252948" Dst="-1" /><file name="Standard_BA_logo_-_blue_writing_red_speedmarque_2013.jpg" server="s99712.gridserver.com//html/mobile/" local="3541600855" remote="319783739185248808" Dst="-1" /><file name="ThomasCook_hori_cmyk.jpg" server="s99712.gridserver.com//html/mobile/" local="3541600855" remote="319783739185253248" Dst="-1" /><file name="Caroline_Strachan.jpg" server="s99712.gridserver.com//html/mobile/" local="3541600848" remote="319783739185416448" Dst="-1" /><file name="Colin_Goldney.jpg" server="s99712.gridserver.com//html/mobile/" local="3541600850" remote="319783739185416268" Dst="-1" /><file name="Dave_Claire.jpg" server="s99712.gridserver.com//html/mobile/" local="3541600850" remote="319783739185416268" Dst="-1" /><file name="Joynt_Jennifer.jpg" server="s99712.gridserver.com//html/mobile/" local="3541600850" remote="319783739185416448" Dst="-1" /><file name="PT_on_stage_2.jpg" server="s99712.gridserver.com//html/mobile/" local="3541600852" remote="319783739185416328" Dst="-1" /><file name="PT_on_stage_2_1.jpg" server="s99712.gridserver.com//html/mobile/" local="3541600853" remote="319783739185416328" Dst="-1" /><file name="Simone_Buckley_-_high_res.png" server="s99712.gridserver.com//html/mobile/" local="3541600854" remote="319783739185416388" Dst="-1" /><file name="Andrew_Cornish.jpg" server="s99712.gridserver.com/html/mobile/" local="3542332380" remote="323953104458593244" Dst="-1" /><file name="Chris_Hadfield_cropped_140x140.jpg" server="s99712.gridserver.com/html/mobile/" local="3542336760" remote="323953104458597624" Dst="-1" /><file name="Colin_Goldney_1.jpg" server="s99712.gridserver.com/html/mobile/" local="3542334660" remote="323953104458595524" Dst="-1" /><file name="daniellevineresizedAPP.jpg" server="s99712.gridserver.com/html/mobile/" local="3542336160" remote="323953104458597024" Dst="-1" /><file name="Dave_Claire_1.jpg" server="s99712.gridserver.com/html/mobile/" local="3542334720" remote="323953104458595584" Dst="-1" /><file name="Dave_Cornthwaite.jpg" server="s99712.gridserver.com/html/mobile/" local="3542333760" remote="323953104458594624" Dst="-1" /><file name="David_Moon.jpg" server="s99712.gridserver.com/html/mobile/" local="3542334060" remote="323953104458594924" Dst="-1" /><file name="Geoff_Ramm_1.jpg" server="s99712.gridserver.com/html/mobile/" local="3542334000" remote="323953104458594864" Dst="-1" /><file name="Jackie_Clark_BAto_use.jpg" server="s99712.gridserver.com/html/mobile/" local="3542655360" remote="323953104458916224" Dst="-1" /><file name="Jo_Kolatis.jpg" server="s99712.gridserver.com/html/mobile/" local="3542336280" remote="323953104458597144" Dst="-1" /><file name="John_s.jpg" server="s99712.gridserver.com/html/mobile/" local="3542600640" remote="323953104458861504" Dst="-1" /><file name="Julia.jpg" server="s99712.gridserver.com/html/mobile/" local="3542336460" remote="323953104458597324" Dst="-1" /><file name="Ken_McLeod.jpg" server="s99712.gridserver.com/html/mobile/" local="3542334180" remote="323953104458595044" Dst="-1" /><file name="Lucy_Huxley.jpg" server="s99712.gridserver.com/html/mobile/" local="3542332020" remote="323953104458592884" Dst="-1" /><file name="Nikki_Rogan.JPG" server="s99712.gridserver.com/html/mobile/" local="3542334300" remote="323953104458595164" Dst="-1" /><file name="Pippa_Jacks.jpg" server="s99712.gridserver.com/html/mobile/" local="3542333580" remote="323953104458594444" Dst="-1" /><file name="PT_on_stage_2_2.jpg" server="s99712.gridserver.com/html/mobile/" local="3542334720" remote="323953104458595584" Dst="-1" /><file name="PT_on_stage_2_3.jpg" server="s99712.gridserver.com/html/mobile/" local="3542334960" remote="323953104458595824" Dst="-1" /><file name="Steven_Alfonso.jpg" server="s99712.gridserver.com/html/mobile/" local="3542336280" remote="323953104458597144" Dst="-1" /></dwsync>